curtsies/__init__.py
curtsies/configfile_keynames.py
curtsies/curtsieskeys.py
curtsies/escseqparse.py
curtsies/events.py
curtsies/fmtfuncs.py
curtsies/formatstring.py
curtsies/formatstringarray.py
curtsies/input.py
curtsies/termformatconstants.py
curtsies/termhelpers.py
curtsies/window.py
curtsies-0.3.3.dist-info/LICENSE
curtsies-0.3.3.dist-info/METADATA
curtsies-0.3.3.dist-info/WHEEL
curtsies-0.3.3.dist-info/top_level.txt
curtsies-0.3.3.dist-info/RECORD
