Metadata-Version: 2.1
Name: curtsies
Version: 0.3.3
Summary: Curses-like terminal wrapper, with colored strings!
Home-page: https://github.com/bpython/curtsies
Author: Thomas Ballinger
Author-email: thomasballinger@gmail.com
License: MIT
Platform: UNKNOWN
Classifier: Development Status :: 3 - Alpha
Classifier: Environment :: Console
Classifier: Intended Audience :: Developers
Classifier: License :: OSI Approved :: MIT License
Classifier: Operating System :: POSIX
Classifier: Programming Language :: Python
Classifier: Programming Language :: Python :: 3
Requires-Dist: blessings (>=1.5)
Requires-Dist: wcwidth (>=0.1.4)
Requires-Dist: typing ; python_version < "3.5"
